LICENSE
MANIFEST.in
README.md
setup.py
cara/__init__.py
cara/cara.py
cara/cara_pseud.py
cara/generics.py
cara/import_hook.py
cara/list_cache.py
cara/type_registry.py
cara.egg-info/PKG-INFO
cara.egg-info/SOURCES.txt
cara.egg-info/dependency_links.txt
cara.egg-info/requires.txt
cara.egg-info/top_level.txt
cara/capnp/__init__.py
cara/capnp/cara.capnp
cara/capnp/cara_capnp.py
cara/capnp/cxx_capnp.py
cara/capnp/generate.sh
cara/capnp/persistent_capnp.py
cara/capnp/rpc_capnp.py
cara/capnp/rpc_twoparty_capnp.py
cara/capnp/schema_capnp.py
docs/advanced_usage.md
docs/changelog.md
docs/differentiations.md
docs/index.md
docs/interfaces.md
docs/remote.md
docs/structs.md
gen/.ycm_extra_conf.py
gen/README.md
gen/capnpc-cara.c++
gen/dodo.py
tests/__init__.py
tests/basics.capnp
tests/basics_capnp.py
tests/basics_test.py
tests/cara_pseud_test.capnp
tests/cara_pseud_test.py
tests/cara_pseud_test_capnp.py
tests/generics_test.capnp
tests/generics_test.py
tests/generics_test_capnp.py
tests/replacing.capnp
tests/replacing_capnp.py
tests/replacing_test.py