Metadata-Version: 1.1
Name: cara
Version: 0.10.0
Summary: cara is a Cap'n proto Alternative RPC API.
Home-page: https://github.com/chainreactionmfg/cara
Author: Fahrzin Hemmati
Author-email: fahhem@gmail.com
License: Apache 2.0
Keywords: cara pseud capnp network rpc schema
Platform: UNKNOWN
Classifier: Development Status :: 2 - Pre-Alpha
Classifier: Intended Audience :: Developers
Classifier: License :: OSI Approved :: Apache Software License
Classifier: Programming Language :: C++
Classifier: Programming Language :: Python
Classifier: Programming Language :: Python :: 3
Classifier: Topic :: Utilities
Classifier: Topic :: System :: Networking
Classifier: Topic :: Software Development :: Code Generators
Classifier: Topic :: Software Development :: Libraries
